{
	"intList" : 
	{
		"arrok 69":[1,1,1,1,1],
		"mitos female facedom" : [ 1, 1, 1, 1],
		"arrok lesbian" : [0, 1 , 1],
		"rohzima stretching girl" : [0 ,0 , 0 ,0, 1],
		"zyn licking":[1,0,1,1],
		"kom naughty girls series":[0,0,0,0,0,0,1],
		"ap standing blowjob":[0,0,1],
		"$zazap_pilloryboundsex02":[1,1,1],
		"$zazap_pillorytorment01":[1,0,0,1,1],
		"$zap_armb_lesbian01" : [0,1,1,1],
		"$zap_armb_lesbian01_ss" : [0,1,1,1],
		"$zazap_sexlablesbianboth" : [0,1,1,1],
		"$zazap_sexlablesbian" :[0,1,1,1],
		"mitos teasing":[1,1],
		"leito cunnilingus":[0,1,1,1,1],
		"kom com pronebone":[1],
		"k4 wallback anal":[1],
		"3jiou threesome" : [ 0, 0, 0, 1, 1, 0, 0, 0, 0, 0, 0, 0, 0, 0, 0, 0 ]
	}
}
